{
  "_downloadMode": "enriched",
  "_garminConnectExtras": {
    "hrTimeInZones": [
      {
        "secsInZone": 8.0,
        "zoneLowBoundary": 129,
        "zoneNumber": 1
      },
      {
        "secsInZone": 12.999,
        "zoneLowBoundary": 145,
        "zoneNumber": 2
      },
      {
        "secsInZone": 7.0,
        "zoneLowBoundary": 165,
        "zoneNumber": 3
      },
      {
        "secsInZone": 529.477,
        "zoneLowBoundary": 171,
        "zoneNumber": 4
      },
      {
        "secsInZone": 53.98,
        "zoneLowBoundary": 181,
        "zoneNumber": 5
      }
    ],
    "powerTimeInZones": [
      {
        "secsInZone": 0.0,
        "zoneLowBoundary": 231,
        "zoneNumber": 1
      },
      {
        "secsInZone": 0.0,
        "zoneLowBoundary": 285,
        "zoneNumber": 2
      },
      {
        "secsInZone": 226.929,
        "zoneLowBoundary": 320,
        "zoneNumber": 3
      },
      {
        "secsInZone": 407.528,
        "zoneLowBoundary": 356,
        "zoneNumber": 4
      },
      {
        "secsInZone": 4.0,
        "zoneLowBoundary": 409,
        "zoneNumber": 5
      }
    ]
  },
  "accessControlRuleDTO": {
    "typeId": 1,
    "typeKey": "public"
  },
  "activityId": 595461610,
  "activityName": "无锡市 操场跑步",
  "activityTypeDTO": {
    "isHidden": false,
    "parentTypeId": 1,
    "restricted": false,
    "trimmable": true,
    "typeId": 8,
    "typeKey": "track_running"
  },
  "activityUUID": {
    "uuid": "537385c8-c539-4b02-8ae6-6ae23b6edebf"
  },
  "eventTypeDTO": {
    "sortOrder": 10,
    "typeId": 9,
    "typeKey": "uncategorized"
  },
  "isMultiSportParent": false,
  "locationName": "无锡市",
  "metadataDTO": {
    "activityImages": [
      {
        "expirationTimestamp": 1781013175632,
        "imageId": "cd49c94c8ae84692b50d146742e3e68f",
        "latitude": null,
        "longitude": null,
        "mediumUrl": "https://garmin-connect-prod.s3.cn-north-1.amazonaws.com.cn/activity_images/cd49c94c8ae84692b50d146742e3e68f-mdfd.jpg?X-Amz-Algorithm=AWS4-HMAC-SHA256&X-Amz-Date=20260608T135255Z&X-Amz-SignedHeaders=host&X-Amz-Expires=86400&X-Amz-Credential=AKIAZ5JW2DRNHWIXPQMX%2F20260608%2Fcn-north-1%2Fs3%2Faws4_request&X-Amz-Signature=7365a5b4a378f578fbf8a2cab831b55eb8570b080b790941c677806231e293be",
        "photoDate": null,
        "smallUrl": "https://garmin-connect-prod.s3.cn-north-1.amazonaws.com.cn/activity_images/cd49c94c8ae84692b50d146742e3e68f-mdfd.jpg?X-Amz-Algorithm=AWS4-HMAC-SHA256&X-Amz-Date=20260608T135255Z&X-Amz-SignedHeaders=host&X-Amz-Expires=86400&X-Amz-Credential=AKIAZ5JW2DRNHWIXPQMX%2F20260608%2Fcn-north-1%2Fs3%2Faws4_request&X-Amz-Signature=7365a5b4a378f578fbf8a2cab831b55eb8570b080b790941c677806231e293be",
        "url": "https://garmin-connect-prod.s3.cn-north-1.amazonaws.com.cn/activity_images/cd49c94c8ae84692b50d146742e3e68f-larg.jpg?X-Amz-Algorithm=AWS4-HMAC-SHA256&X-Amz-Date=20260608T135255Z&X-Amz-SignedHeaders=host&X-Amz-Expires=86400&X-Amz-Credential=AKIAZ5JW2DRNHWIXPQMX%2F20260608%2Fcn-north-1%2Fs3%2Faws4_request&X-Amz-Signature=30f8ae54d42ea1f884add08c18516cb6a50cc6908cac0169470ef200b47d8042"
      },
      {
        "expirationTimestamp": 1781013175632,
        "imageId": "abe76a01d6834e8c8730c0c3605c272a",
        "latitude": null,
        "longitude": null,
        "mediumUrl": "https://garmin-connect-prod.s3.cn-north-1.amazonaws.com.cn/activity_images/abe76a01d6834e8c8730c0c3605c272a-mdfd.jpg?X-Amz-Algorithm=AWS4-HMAC-SHA256&X-Amz-Date=20260608T135255Z&X-Amz-SignedHeaders=host&X-Amz-Expires=86400&X-Amz-Credential=AKIAZ5JW2DRNHWIXPQMX%2F20260608%2Fcn-north-1%2Fs3%2Faws4_request&X-Amz-Signature=670a243b66d57ad375b3e2cc72d9ce0bd402d2a8a6a28d6c0314a34e0128e1dd",
        "photoDate": null,
        "smallUrl": "https://garmin-connect-prod.s3.cn-north-1.amazonaws.com.cn/activity_images/abe76a01d6834e8c8730c0c3605c272a-mdfd.jpg?X-Amz-Algorithm=AWS4-HMAC-SHA256&X-Amz-Date=20260608T135255Z&X-Amz-SignedHeaders=host&X-Amz-Expires=86400&X-Amz-Credential=AKIAZ5JW2DRNHWIXPQMX%2F20260608%2Fcn-north-1%2Fs3%2Faws4_request&X-Amz-Signature=670a243b66d57ad375b3e2cc72d9ce0bd402d2a8a6a28d6c0314a34e0128e1dd",
        "url": "https://garmin-connect-prod.s3.cn-north-1.amazonaws.com.cn/activity_images/abe76a01d6834e8c8730c0c3605c272a-larg.jpg?X-Amz-Algorithm=AWS4-HMAC-SHA256&X-Amz-Date=20260608T135255Z&X-Amz-SignedHeaders=host&X-Amz-Expires=86400&X-Amz-Credential=AKIAZ5JW2DRNHWIXPQMX%2F20260608%2Fcn-north-1%2Fs3%2Faws4_request&X-Amz-Signature=407c509eb26ad300979d93d5021ea11c08750e3b2bfd5aeb7df6e7a8eadf9be5"
      },
      {
        "expirationTimestamp": 1781013175632,
        "imageId": "b69e2543f8974125a874d5ef96cbc620",
        "latitude": null,
        "longitude": null,
        "mediumUrl": "https://garmin-connect-prod.s3.cn-north-1.amazonaws.com.cn/activity_images/b69e2543f8974125a874d5ef96cbc620-mdfd.jpg?X-Amz-Algorithm=AWS4-HMAC-SHA256&X-Amz-Date=20260608T135255Z&X-Amz-SignedHeaders=host&X-Amz-Expires=86400&X-Amz-Credential=AKIAZ5JW2DRNHWIXPQMX%2F20260608%2Fcn-north-1%2Fs3%2Faws4_request&X-Amz-Signature=2028b6300aecacf184b567123422b089526ab71af60aaece9ea37537d5f45020",
        "photoDate": null,
        "smallUrl": "https://garmin-connect-prod.s3.cn-north-1.amazonaws.com.cn/activity_images/b69e2543f8974125a874d5ef96cbc620-mdfd.jpg?X-Amz-Algorithm=AWS4-HMAC-SHA256&X-Amz-Date=20260608T135255Z&X-Amz-SignedHeaders=host&X-Amz-Expires=86400&X-Amz-Credential=AKIAZ5JW2DRNHWIXPQMX%2F20260608%2Fcn-north-1%2Fs3%2Faws4_request&X-Amz-Signature=2028b6300aecacf184b567123422b089526ab71af60aaece9ea37537d5f45020",
        "url": "https://garmin-connect-prod.s3.cn-north-1.amazonaws.com.cn/activity_images/b69e2543f8974125a874d5ef96cbc620-larg.jpg?X-Amz-Algorithm=AWS4-HMAC-SHA256&X-Amz-Date=20260608T135255Z&X-Amz-SignedHeaders=host&X-Amz-Expires=86400&X-Amz-Credential=AKIAZ5JW2DRNHWIXPQMX%2F20260608%2Fcn-north-1%2Fs3%2Faws4_request&X-Amz-Signature=458d026813a12379cbe449aa4da4a5f7975a3ba8c4dbe4a18b0f1ff68552baf9"
      }
    ],
    "agentApplicationInstallationId": null,
    "agentString": null,
    "associatedCourseId": null,
    "associatedWorkoutId": null,
    "autoCalcCalories": false,
    "calendarEventInfo": null,
    "childActivityTypes": [],
    "childIds": [],
    "deviceApplicationInstallationId": 860311,
    "deviceMetaDataDTO": {
      "deviceId": "3600896256",
      "deviceTypePk": 45479,
      "deviceVersionPk": 860311
    },
    "diveNumber": null,
    "eBikeAssistModeInfoDTOList": null,
    "eBikeBatteryRemaining": null,
    "eBikeBatteryUsage": null,
    "eBikeMaxAssistModes": null,
    "elevationCorrected": false,
    "favorite": true,
    "fileFormat": {
      "formatId": 7,
      "formatKey": "fit"
    },
    "gcj02": false,
    "groupRideUUID": null,
    "hasChartData": true,
    "hasHeatMap": false,
    "hasHrTimeInZones": true,
    "hasIntensityIntervals": false,
    "hasPolyline": true,
    "hasPowerTimeInZones": true,
    "hasRunPowerWindData": false,
    "hasSplits": true,
    "isAtpActivity": null,
    "isOriginal": true,
    "lapCount": 8,
    "lastUpdateDate": "2026-05-31T15:09:12.0",
    "manualActivity": false,
    "manufacturer": "GARMIN",
    "personalRecord": false,
    "runPowerWindDataEnabled": true,
    "sensors": null,
    "trimmed": false,
    "uploadedDate": "2026-05-16T11:47:22.0",
    "userInfoDto": {
      "displayname": "dccfdc6a-96f5-40b0-9d47-b7f60b9b7f17",
      "fullname": "陈振",
      "profileImageUrlLarge": "https://s3.cn-north-1.amazonaws.com.cn/garmin-connect-prod/profile_images/fca23093-4f2d-42c6-971d-054a20d10139-prof.png",
      "profileImageUrlMedium": "https://s3.cn-north-1.amazonaws.com.cn/garmin-connect-prod/profile_images/fca23093-4f2d-42c6-971d-054a20d10139-prfr.png",
      "profileImageUrlSmall": "https://s3.cn-north-1.amazonaws.com.cn/garmin-connect-prod/profile_images/fca23093-4f2d-42c6-971d-054a20d10139-prth.png",
      "userPro": false,
      "userProfilePk": 12733831
    },
    "videoUrl": null
  },
  "splitSummaries": [
    {
      "averageElevationGain": 2.0,
      "averageHR": 173.0,
      "averageMovingSpeed": 4.710485133020344,
      "averagePower": 357.0,
      "averageRunCadence": 194.296875,
      "averageSpeed": 4.681000232696533,
      "avgStepFrequency": 194.296875,
      "avgStepLength": 1.406,
      "avgVerticalSpeed": 0.0030000000260770325,
      "bmrCalories": 14.0,
      "calories": 156.0,
      "distance": 3010.0,
      "duration": 643.077,
      "elevationGain": 2.0,
      "elevationLoss": 0.0,
      "groundContactTime": 193.39999389648438,
      "maxDistance": 3010,
      "maxDistanceWithPrecision": 3010.0,
      "maxElevationGain": 2.0,
      "maxHR": 182.0,
      "maxPower": 426.0,
      "maxRunCadence": 203.0,
      "maxSpeed": 5.552000045776367,
      "movingDuration": 639.0,
      "noOfSplits": 1,
      "normalizedPower": 359.0,
      "splitType": "INTERVAL_ACTIVE",
      "strideLength": 140.6,
      "totalExerciseReps": 0,
      "verticalOscillation": 8.51999969482422,
      "verticalRatio": 6.059999942779541
    },
    {
      "averageElevationGain": 2.0,
      "averageHR": 173.0,
      "averageMovingSpeed": 4.705664979460094,
      "averagePower": 357.0,
      "averageRunCadence": 194.296875,
      "averageSpeed": 4.676000118255615,
      "avgStepFrequency": 194.296875,
      "avgStepLength": 1.406,
      "avgVerticalSpeed": 0.0030000000260770325,
      "bmrCalories": 14.0,
      "calories": 156.0,
      "distance": 3006.92,
      "duration": 643.045,
      "elevationGain": 2.0,
      "elevationLoss": 0.0,
      "groundContactTime": 193.39999389648438,
      "maxDistance": 3006,
      "maxDistanceWithPrecision": 3006.92,
      "maxElevationGain": 2.0,
      "maxHR": 182.0,
      "maxPower": 426.0,
      "maxRunCadence": 203.0,
      "maxSpeed": 5.552000045776367,
      "movingDuration": 639.0,
      "noOfSplits": 1,
      "normalizedPower": 359.0,
      "splitType": "RWD_RUN",
      "strideLength": 140.6,
      "totalExerciseReps": 0,
      "verticalOscillation": 8.51999969482422,
      "verticalRatio": 6.059999942779541
    }
  ],
  "summaryDTO": {
    "activityTrainingLoad": 144.24026489257812,
    "aerobicTrainingEffectMessage": "MAINTAINING_TEMPO_21",
    "anaerobicTrainingEffect": 2.5999999046325684,
    "anaerobicTrainingEffectMessage": "MAINTAINING_ANAEROBIC_BASE_1",
    "averageHR": 173.0,
    "averageMovingSpeed": 4.715717380152602,
    "averagePower": 357.0,
    "averageRunCadence": 194.3125,
    "averageSpeed": 4.681000232696533,
    "avgElevation": 6.42,
    "bmrCalories": 14.0,
    "calories": 156.0,
    "differenceBodyBattery": -5,
    "distance": 3010.0,
    "duration": 643.077,
    "elapsedDuration": 643.077,
    "elevationGain": 2.0,
    "elevationLoss": 0.0,
    "endLatitude": 31.488604685291648,
    "endLongitude": 120.27042900212109,
    "groundContactTime": 193.39999389648438,
    "maxElevation": 10.0,
    "maxHR": 182.0,
    "maxPower": 426.0,
    "maxRunCadence": 203.0,
    "maxSpeed": 5.552000045776367,
    "maxVerticalSpeed": 5.0,
    "minActivityLapDuration": 43.312,
    "minElevation": 3.0,
    "minHR": 82.0,
    "minPower": 0.0,
    "moderateIntensityMinutes": 0,
    "movingDuration": 638.291,
    "normalizedPower": 359.0,
    "startLatitude": 31.489418232813478,
    "startLongitude": 120.27120717801154,
    "startTimeGMT": "2026-05-16T10:39:56.0",
    "startTimeLocal": "2026-05-16T18:39:56.0",
    "steps": 2072,
    "strideLength": 140.6,
    "totalWork": 54.892339416040976,
    "trainingEffect": 2.9000000953674316,
    "trainingEffectLabel": "TEMPO",
    "verticalOscillation": 8.51999969482422,
    "verticalRatio": 6.059999942779541,
    "vigorousIntensityMinutes": 6,
    "waterEstimated": 178.0
  },
  "timeZoneUnitDTO": {
    "factor": 0.0,
    "timeZone": "Asia/Hong_Kong",
    "unitId": 135,
    "unitKey": "Asia/Hong_Kong"
  },
  "userProfileId": 12733831
}