{
  "_downloadMode": "enriched",
  "_garminConnectExtras": {
    "hrTimeInZones": [
      {
        "secsInZone": 0.0,
        "zoneLowBoundary": 93,
        "zoneNumber": 1
      },
      {
        "secsInZone": 25.0,
        "zoneLowBoundary": 111,
        "zoneNumber": 2
      },
      {
        "secsInZone": 30.0,
        "zoneLowBoundary": 130,
        "zoneNumber": 3
      },
      {
        "secsInZone": 1066.0,
        "zoneLowBoundary": 148,
        "zoneNumber": 4
      },
      {
        "secsInZone": 480.0,
        "zoneLowBoundary": 167,
        "zoneNumber": 5
      }
    ],
    "powerTimeInZones": []
  },
  "accessControlRuleDTO": {
    "typeId": 1,
    "typeKey": "public"
  },
  "activityId": 575221775,
  "activityName": "无锡市 街道路跑",
  "activityTypeDTO": {
    "isHidden": false,
    "parentTypeId": 1,
    "restricted": false,
    "trimmable": true,
    "typeId": 7,
    "typeKey": "street_running"
  },
  "activityUUID": {
    "uuid": "a1e23abf-ac44-4c45-89f8-b05b6c055962"
  },
  "eventTypeDTO": {
    "sortOrder": 10,
    "typeId": 9,
    "typeKey": "uncategorized"
  },
  "isMultiSportParent": false,
  "locationName": "无锡市",
  "metadataDTO": {
    "activityImages": [],
    "agentApplicationInstallationId": null,
    "agentString": null,
    "associatedCourseId": null,
    "associatedWorkoutId": null,
    "autoCalcCalories": false,
    "calendarEventInfo": null,
    "childActivityTypes": [],
    "childIds": [],
    "deviceApplicationInstallationId": 80,
    "deviceMetaDataDTO": {
      "deviceId": "12345",
      "deviceTypePk": 19,
      "deviceVersionPk": 80
    },
    "diveNumber": null,
    "eBikeAssistModeInfoDTOList": null,
    "eBikeBatteryRemaining": null,
    "eBikeBatteryUsage": null,
    "eBikeMaxAssistModes": null,
    "elevationCorrected": false,
    "favorite": false,
    "fileFormat": {
      "formatId": 7,
      "formatKey": "fit"
    },
    "gcj02": false,
    "groupRideUUID": null,
    "hasChartData": true,
    "hasHeatMap": false,
    "hasHrTimeInZones": true,
    "hasIntensityIntervals": false,
    "hasPolyline": true,
    "hasPowerTimeInZones": false,
    "hasRunPowerWindData": null,
    "hasSplits": false,
    "isAtpActivity": null,
    "isOriginal": true,
    "lapCount": 7,
    "lastUpdateDate": "2026-03-27T06:13:44.0",
    "manualActivity": false,
    "manufacturer": "DEVELOPMENT",
    "personalRecord": false,
    "runPowerWindDataEnabled": null,
    "sensors": null,
    "trimmed": false,
    "uploadedDate": "2026-03-19T12:21:35.0",
    "userInfoDto": {
      "displayname": "dccfdc6a-96f5-40b0-9d47-b7f60b9b7f17",
      "fullname": "陈振",
      "profileImageUrlLarge": "https://s3.cn-north-1.amazonaws.com.cn/garmin-connect-prod/profile_images/fca23093-4f2d-42c6-971d-054a20d10139-prof.png",
      "profileImageUrlMedium": "https://s3.cn-north-1.amazonaws.com.cn/garmin-connect-prod/profile_images/fca23093-4f2d-42c6-971d-054a20d10139-prfr.png",
      "profileImageUrlSmall": "https://s3.cn-north-1.amazonaws.com.cn/garmin-connect-prod/profile_images/fca23093-4f2d-42c6-971d-054a20d10139-prth.png",
      "userPro": false,
      "userProfilePk": 12733831
    },
    "videoUrl": null
  },
  "summaryDTO": {
    "averageHR": 162.0,
    "averageMovingSpeed": 4.378513429106809,
    "averageRunCadence": 194.0,
    "averageSpeed": 4.364999771118164,
    "avgElevation": 4.6,
    "calories": 364.0,
    "distance": 7010.0,
    "duration": 1606.0,
    "elapsedDuration": 1606.0,
    "elevationGain": 15.0,
    "elevationLoss": 18.0,
    "endLatitude": 31.48703383281827,
    "endLongitude": 120.26852413080633,
    "maxElevation": 8.6,
    "maxHR": 171.0,
    "maxRunCadence": 198.0,
    "maxSpeed": 0.0,
    "maxVerticalSpeed": 0.9158446311950683,
    "minActivityLapDuration": 216.0,
    "minElevation": 0.6,
    "minHR": 113.0,
    "movingDuration": 1601.0,
    "startLatitude": 31.487905466929078,
    "startLongitude": 120.27077483944595,
    "startTimeGMT": "2026-03-07T06:44:37.0",
    "startTimeLocal": "2026-03-07T14:44:37.0",
    "strideLength": 67.25800459437686
  },
  "timeZoneUnitDTO": {
    "factor": 0.0,
    "timeZone": "Asia/Hong_Kong",
    "unitId": 135,
    "unitKey": "Asia/Hong_Kong"
  },
  "userProfileId": 12733831
}